orchestron/__about__.py
orchestron/__init__.py
orchestron-0.0.2.dist-info/METADATA
orchestron-0.0.2.dist-info/WHEEL
orchestron-0.0.2.dist-info/licenses/LICENSE.txt
orchestron-0.0.2.dist-info/RECORD
